{
  "generated_at": "2026-02-26T04:12:51.141465",
  "total_applications": 88,
  "categories": {
    "backend": 56,
    "frontend": 26,
    "database": 26,
    "networking": 11,
    "data-science": 44,
    "system": 14,
    "data-analyst": 36,
    "pm": 5,
    "sap-abap": 2,
    "mobile": 34,
    "qa": 2,
    "game": 5,
    "embedded": 9,
    "cyber-security": 8,
    "hardware": 8,
    "": 1,
    "blockchain": 3
  },
  "locations": {
    "yüzyüze": 79,
    "uzaktan": 57
  },
  "intern_types": {
    "zorunlu": 65,
    "gönüllü": 19,
    "gönüllü, zorunlu": 1,
    "zorunlu, gönüllü": 1,
    "zorunlu,gönüllü": 1
  },
  "durations": {
    "4-hafta": 60,
    "6-hafta": 35,
    "8-hafta": 44,
    "[4-hafta": 1
  },
  "recent_applications": 2,
  "this_week_applications": 87,
  "this_month_applications": 87
}